nhl_api_client/__init__.py
nhl_api_client/client.py
nhl_stats_api_client-1.0.3.dist-info/licenses/LICENSE
nhl_stats_api_client-1.0.3.dist-info/METADATA
nhl_stats_api_client-1.0.3.dist-info/WHEEL
nhl_stats_api_client-1.0.3.dist-info/top_level.txt
nhl_stats_api_client-1.0.3.dist-info/RECORD
