Metadata-Version: 2.4
Name: nhl-stats-api-client
Version: 1.0.3
Summary: A comprehensive Python client for accessing NHL statistics and data
Home-page: https://github.com/liahimratman/nhl-api-client
Author: Mikhail Korotkov
Author-email: Mikhail Korotkov <ma.korotkov.eu@gmail.com>
Maintainer-email: Mikhail Korotkov <ma.korotkov.eu@gmail.com>
License: MIT
Project-URL: Homepage, https://github.com/liahimratman/nhl-api-client
Project-URL: Documentation, https://github.com/liahimratman/nhl-api-client#readme
Project-URL: Repository, https://github.com/liahimratman/nhl-api-client
Project-URL: Bug Reports, https://github.com/liahimratman/nhl-api-client/issues
Keywords: nhl,hockey,api,statistics,sports,analytics
Classifier: Development Status :: 5 - Production/Stable
Classifier: Intended Audience :: Developers
Classifier: License :: OSI Approved :: MIT License
Classifier: Operating System :: OS Independent
Classifier: Programming Language :: Python :: 3
Classifier: Programming Language :: Python :: 3.8
Classifier: Programming Language :: Python :: 3.9
Classifier: Programming Language :: Python :: 3.10
Classifier: Programming Language :: Python :: 3.11
Classifier: Programming Language :: Python :: 3.12
Classifier: Topic :: Software Development :: Libraries :: Python Modules
Classifier: Topic :: Internet :: WWW/HTTP :: Dynamic Content
Requires-Python: >=3.8
License-File: LICENSE
Requires-Dist: requests>=2.25.0
Requires-Dist: pandas>=1.3.0
Provides-Extra: dev
Requires-Dist: pytest>=6.0; extra == "dev"
Requires-Dist: pytest-cov>=2.0; extra == "dev"
Requires-Dist: black>=21.0; extra == "dev"
Requires-Dist: flake8>=3.8; extra == "dev"
Requires-Dist: mypy>=0.800; extra == "dev"
Dynamic: author
Dynamic: home-page
Dynamic: license-file
Dynamic: requires-python
